LICENSE
MANIFEST.in
README.md
requirements.txt
setup.py
certstream/__init__.py
certstream/cli.py
certstream/core.py
certstream.egg-info/PKG-INFO
certstream.egg-info/SOURCES.txt
certstream.egg-info/dependency_links.txt
certstream.egg-info/entry_points.txt
certstream.egg-info/requires.txt
certstream.egg-info/top_level.txt